scratchattach/__init__.py
scratchattach/_cloud.py
scratchattach/_cloud_requests.py
scratchattach/_encoder.py
scratchattach/_exceptions.py
scratchattach/_project.py
scratchattach/_session.py
scratchattach/_user.py
scratch3.py-0.4.5.dist-info/METADATA
scratch3.py-0.4.5.dist-info/WHEEL
scratch3.py-0.4.5.dist-info/top_level.txt
scratch3.py-0.4.5.dist-info/RECORD
