Metadata-Version: 2.1
Name: scratch3.py
Version: 0.4.5
Summary: An Scratch API Wrapper for scratch.mit.edu
Home-page: https://github.com/TimMcCool/scratchattach
Author: TimMcCool
Author-email: timmccool.scratch@gmail.com
License: UNKNOWN
Keywords: scratch api,scratchattach,scratch api python,scratch python,scratch for python,scratch,scratch cloud,scratch cloud variables,scratch bot
Platform: UNKNOWN
Classifier: Development Status :: 5 - Production/Stable
Classifier: Intended Audience :: Developers
Classifier: Programming Language :: Python :: 3
Classifier: Operating System :: Unix
Classifier: Operating System :: MacOS :: MacOS X
Classifier: Operating System :: Microsoft :: Windows
Requires-Dist: websocket-client
Requires-Dist: numpy
Requires-Dist: requests
